setup.py
funpack/__init__.py
funpack/ping.py
funpack.egg-info/PKG-INFO
funpack.egg-info/SOURCES.txt
funpack.egg-info/dependency_links.txt
funpack.egg-info/not-zip-safe
funpack.egg-info/requires.txt
funpack.egg-info/top_level.txt