Metadata-Version: 1.0
Name: funpack
Version: 0.5
Summary: Get google home link repond
Home-page: https://github.cerner.com/cs049571/lib_dep_tryouts
Author: Chintan Soni
Author-email: chintan.soni@cerner.com
License: Cerner
Platform: UNKNOWN
